fed/__init__.py
fed/api.py
fed/cleanup.py
fed/config.py
fed/exceptions.py
fed/fed_object.py
fed/tree_util.py
fed/utils.py
fed/_private/__init__.py
fed/_private/compatible_utils.py
fed/_private/constants.py
fed/_private/fed_actor.py
fed/_private/fed_call_holder.py
fed/_private/global_context.py
fed/_private/message_queue.py
fed/_private/serialization_utils.py
fed/grpc/__init__.py
fed/grpc/pb3/__init__.py
fed/grpc/pb3/fed_pb2.py
fed/grpc/pb3/fed_pb2_grpc.py
fed/grpc/pb4/__init__.py
fed/grpc/pb4/fed_pb2.py
fed/grpc/pb4/fed_pb2_grpc.py
fed/proxy/__init__.py
fed/proxy/barriers.py
fed/proxy/base_proxy.py
fed/proxy/grpc/__init__.py
fed/proxy/grpc/grpc_options.py
fed/proxy/grpc/grpc_proxy.py
fed/tests/__init__.py
fed/tests/simple_example.py
fed/tests/test_api.py
fed/tests/test_async_startup_2_clusters.py
fed/tests/test_basic_pass_fed_objects.py
fed/tests/test_cache_fed_objects.py
fed/tests/test_cross_silo_error.py
fed/tests/test_enable_tls_across_parties.py
fed/tests/test_exit_on_failure_sending.py
fed/tests/test_fed_get.py
fed/tests/test_grpc_options_on_proxies.py
fed/tests/test_internal_kv.py
fed/tests/test_listening_address.py
fed/tests/test_options.py
fed/tests/test_pass_fed_objects_in_containers_in_actor.py
fed/tests/test_pass_fed_objects_in_containers_in_normal_tasks.py
fed/tests/test_ping_others.py
fed/tests/test_repeat_init.py
fed/tests/test_reset_context.py
fed/tests/test_retry_policy.py
fed/tests/test_setup_proxy_actor.py
fed/tests/test_transport_proxy.py
fed/tests/test_transport_proxy_tls.py
fed/tests/test_utils.py
fed/tests/client_mode_tests/__init__.py
fed/tests/client_mode_tests/test_basic_client_mode.py
fed/tests/multi-jobs/__init__.py
fed/tests/multi-jobs/test_ignore_other_job_msg.py
fed/tests/multi-jobs/test_multi_proxy_actor.py
fed/tests/serializations_tests/__init__.py
fed/tests/serializations_tests/test_unpickle_with_whitelist.py
fed/tests/without_ray_tests/__init__.py
fed/tests/without_ray_tests/test_tree_utils.py
rayfed_nightly-0.1.0b20240201.dev0.dist-info/LICENSE
rayfed_nightly-0.1.0b20240201.dev0.dist-info/METADATA
rayfed_nightly-0.1.0b20240201.dev0.dist-info/WHEEL
rayfed_nightly-0.1.0b20240201.dev0.dist-info/top_level.txt
rayfed_nightly-0.1.0b20240201.dev0.dist-info/RECORD
