Metadata-Version: 2.1
Name: rayfed-nightly
Version: 0.1.0b20240201.dev0
Summary: A multiple parties joint, distributed execution engine based on Ray,to help build your own federated learning frameworks in minutes.
Home-page: https://github.com/ray-project/rayfed
Author: RayFed Team
Author-email: rayfed-dev@googlegroups.com
License: Apache 2.0
Platform: UNKNOWN
License-File: LICENSE
Requires-Dist: ray >=1.13.0
Requires-Dist: cloudpickle
Requires-Dist: protobuf
Requires-Dist: grpcio >=1.42.0
Requires-Dist: pickle5 ==0.0.11 ; python_version < "3.8"
Provides-Extra: dev
Requires-Dist: pylint ; extra == 'dev'
